melvec/__init__.py
melvec/vec2.py
melvec/vec3.py
melvec/vec_base.py
melvec-0.0.10.dist-info/LICENSE
melvec-0.0.10.dist-info/METADATA
melvec-0.0.10.dist-info/WHEEL
melvec-0.0.10.dist-info/top_level.txt
melvec-0.0.10.dist-info/RECORD
